src/__init__.py
src/app.py
src/cli.py
src/main.py
src/market_data.py
src/utils.py
src/converters/__init__.py
src/converters/base.py
src/converters/binance.py
src/converters/coinbase.py
src/converters/inversis.py
src/converters/myinvestor.py
src/converters/xtb.py
portfolio_performance_converter-0.2.0.dist-info/METADATA
portfolio_performance_converter-0.2.0.dist-info/WHEEL
portfolio_performance_converter-0.2.0.dist-info/entry_points.txt
portfolio_performance_converter-0.2.0.dist-info/licenses/LICENSE
portfolio_performance_converter-0.2.0.dist-info/RECORD
