Metadata-Version: 2.4
Name: portfolio-performance-converter
Version: 0.2.0
Summary: Tool to convert exports from various brokers to a CSV format compatible with Portfolio Performance.
Author-email: Martín Molina Álvarez <contact@marmol.dev>
License-File: LICENSE
Requires-Python: >=3.10
Requires-Dist: gradio
Requires-Dist: html5lib
Requires-Dist: lxml
Requires-Dist: openpyxl
Requires-Dist: pandas
Requires-Dist: pyyaml
Requires-Dist: websockets>=13.0
Requires-Dist: yfinance
